vision_transformer_pytorch/__init__.py
vision_transformer_pytorch/model.py
vision_transformer_pytorch/resnet.py
vision_transformer_pytorch/utils.py
vision_transformer_pytorch-1.0.3.dist-info/LICENSE
vision_transformer_pytorch-1.0.3.dist-info/METADATA
vision_transformer_pytorch-1.0.3.dist-info/WHEEL
vision_transformer_pytorch-1.0.3.dist-info/top_level.txt
vision_transformer_pytorch-1.0.3.dist-info/RECORD
