Metadata-Version: 2.1
Name: vision-transformer-pytorch
Version: 1.0.3
Summary: VisionTransformer implemented in PyTorch.
Home-page: https://github.com/tczhangzhi/VisionTransformer-PyTorch
Author: ZHANG Zhi
Author-email: zhangzhi2018@email.szu.edu.cn
License: Apache
Platform: UNKNOWN
Classifier: License :: OSI Approved :: Apache Software License
Classifier: Programming Language :: Python
Classifier: Programming Language :: Python :: 3
Classifier: Programming Language :: Python :: 3.6
Requires-Python: >=3.5.0
Requires-Dist: torch (>=1.5.0)
Requires-Dist: numpy
